performanceTester/__init__.py
performanceTester/perfTester.py
pTestingforTime-0.2.dist-info/METADATA
pTestingforTime-0.2.dist-info/WHEEL
pTestingforTime-0.2.dist-info/top_level.txt
pTestingforTime-0.2.dist-info/RECORD
