Metadata-Version: 2.1
Name: pTestingforTime
Version: 0.2
Summary: Tests the performance of functions according by time
Author: Tolga
